{
  "-36,-33": {
    "SourceVersionHash": "g8USaPZtnnDKO8S0aUUJJuCyUbc=",
    "VersionHash": "hfTN+UitZdZSY5/Ol/C9Lqf3dn8="
  },
  "-36,-34": {
    "SourceVersionHash": "g8USaPZtnnDKO8S0aUUJJuCyUbc=",
    "VersionHash": "hfTN+UitZdZSY5/Ol/C9Lqf3dn8="
  },
  "-36,-35": {
    "SourceVersionHash": "P8fCGfLssgva/SnVnKUxTvej03I=",
    "VersionHash": "hfTN+UitZdZSY5/Ol/C9Lqf3dn8="
  },
  "-36,-38": {
    "SourceVersionHash": "S+5IW/0PK19bAiKngJ1HdvXg69w=",
    "VersionHash": "hfTN+UitZdZSY5/Ol/C9Lqf3dn8="
  },
  "-36,-37": {
    "SourceVersionHash": "S+5IW/0PK19bAiKngJ1HdvXg69w=",
    "VersionHash": "hfTN+UitZdZSY5/Ol/C9Lqf3dn8="
  },
  "-36,-40": {
    "SourceVersionHash": "fs4tm5i6ZbLwE2mMeqksuyDCYmU=",
    "VersionHash": "hfTN+UitZdZSY5/Ol/C9Lqf3dn8="
  },
  "-36,-39": {
    "SourceVersionHash": "fs4tm5i6ZbLwE2mMeqksuyDCYmU=",
    "VersionHash": "hfTN+UitZdZSY5/Ol/C9Lqf3dn8="
  },
  "-36,-36": {
    "SourceVersionHash": "P8fCGfLssgva/SnVnKUxTvej03I=",
    "VersionHash": "hfTN+UitZdZSY5/Ol/C9Lqf3dn8="
  },
  "-34,-42": {
    "SourceVersionHash": "ifyYzTKpkaq77Axe7WCxio0syf4=",
    "VersionHash": "hfTN+UitZdZSY5/Ol/C9Lqf3dn8="
  },
  "-33,-42": {
    "SourceVersionHash": "ifyYzTKpkaq77Axe7WCxio0syf4=",
    "VersionHash": "hfTN+UitZdZSY5/Ol/C9Lqf3dn8="
  },
  "-34,-40": {
    "SourceVersionHash": "AIZRt3pICahtuRkA5sF/2tQvlmU=",
    "VersionHash": "hfTN+UitZdZSY5/Ol/C9Lqf3dn8="
  },
  "-35,-40": {
    "SourceVersionHash": "fs4tm5i6ZbLwE2mMeqksuyDCYmU=",
    "VersionHash": "hfTN+UitZdZSY5/Ol/C9Lqf3dn8="
  },
  "-34,-41": {
    "SourceVersionHash": "ifyYzTKpkaq77Axe7WCxio0syf4=",
    "VersionHash": "hfTN+UitZdZSY5/Ol/C9Lqf3dn8="
  },
  "-34,-38": {
    "SourceVersionHash": "v3MwsTv689MuVK/puJ+gahy5SGk=",
    "VersionHash": "hfTN+UitZdZSY5/Ol/C9Lqf3dn8="
  },
  "-35,-38": {
    "SourceVersionHash": "S+5IW/0PK19bAiKngJ1HdvXg69w=",
    "VersionHash": "hfTN+UitZdZSY5/Ol/C9Lqf3dn8="
  },
  "-35,-39": {
    "SourceVersionHash": "fs4tm5i6ZbLwE2mMeqksuyDCYmU=",
    "VersionHash": "hfTN+UitZdZSY5/Ol/C9Lqf3dn8="
  },
  "-34,-39": {
    "SourceVersionHash": "AIZRt3pICahtuRkA5sF/2tQvlmU=",
    "VersionHash": "hfTN+UitZdZSY5/Ol/C9Lqf3dn8="
  },
  "-33,-40": {
    "SourceVersionHash": "AIZRt3pICahtuRkA5sF/2tQvlmU=",
    "VersionHash": "r5yH8hwGPQGpp+s7MTm+GpVd4TA="
  },
  "-33,-41": {
    "SourceVersionHash": "ifyYzTKpkaq77Axe7WCxio0syf4=",
    "VersionHash": "r5yH8hwGPQGpp+s7MTm+GpVd4TA="
  },
  "-33,-38": {
    "SourceVersionHash": "v3MwsTv689MuVK/puJ+gahy5SGk=",
    "VersionHash": "r5yH8hwGPQGpp+s7MTm+GpVd4TA="
  },
  "-33,-39": {
    "SourceVersionHash": "AIZRt3pICahtuRkA5sF/2tQvlmU=",
    "VersionHash": "r5yH8hwGPQGpp+s7MTm+GpVd4TA="
  },
  "-35,-36": {
    "SourceVersionHash": "P8fCGfLssgva/SnVnKUxTvej03I=",
    "VersionHash": "r5yH8hwGPQGpp+s7MTm+GpVd4TA="
  },
  "-34,-36": {
    "SourceVersionHash": "V5gFuUSAWEOfGvTqPsPpe4PtxdY=",
    "VersionHash": "r5yH8hwGPQGpp+s7MTm+GpVd4TA="
  },
  "-34,-37": {
    "SourceVersionHash": "v3MwsTv689MuVK/puJ+gahy5SGk=",
    "VersionHash": "r5yH8hwGPQGpp+s7MTm+GpVd4TA="
  },
  "-33,-37": {
    "SourceVersionHash": "v3MwsTv689MuVK/puJ+gahy5SGk=",
    "VersionHash": "r5yH8hwGPQGpp+s7MTm+GpVd4TA="
  },
  "-33,-36": {
    "SourceVersionHash": "V5gFuUSAWEOfGvTqPsPpe4PtxdY=",
    "VersionHash": "r5yH8hwGPQGpp+s7MTm+GpVd4TA="
  },
  "-35,-37": {
    "SourceVersionHash": "S+5IW/0PK19bAiKngJ1HdvXg69w=",
    "VersionHash": "r5yH8hwGPQGpp+s7MTm+GpVd4TA="
  },
  "-35,-35": {
    "SourceVersionHash": "P8fCGfLssgva/SnVnKUxTvej03I=",
    "VersionHash": "r5yH8hwGPQGpp+s7MTm+GpVd4TA="
  },
  "-34,-35": {
    "SourceVersionHash": "V5gFuUSAWEOfGvTqPsPpe4PtxdY=",
    "VersionHash": "r5yH8hwGPQGpp+s7MTm+GpVd4TA="
  },
  "-35,-34": {
    "SourceVersionHash": "g8USaPZtnnDKO8S0aUUJJuCyUbc=",
    "VersionHash": "r5yH8hwGPQGpp+s7MTm+GpVd4TA="
  },
  "-34,-34": {
    "SourceVersionHash": "PjFa6jxycfFw/siKVn4ZofJRiI0=",
    "VersionHash": "r5yH8hwGPQGpp+s7MTm+GpVd4TA="
  },
  "-33,-34": {
    "SourceVersionHash": "PjFa6jxycfFw/siKVn4ZofJRiI0=",
    "VersionHash": "r5yH8hwGPQGpp+s7MTm+GpVd4TA="
  },
  "-33,-35": {
    "SourceVersionHash": "V5gFuUSAWEOfGvTqPsPpe4PtxdY=",
    "VersionHash": "r5yH8hwGPQGpp+s7MTm+GpVd4TA="
  },
  "-35,-33": {
    "SourceVersionHash": "g8USaPZtnnDKO8S0aUUJJuCyUbc=",
    "VersionHash": "r5yH8hwGPQGpp+s7MTm+GpVd4TA="
  },
  "-34,-33": {
    "SourceVersionHash": "PjFa6jxycfFw/siKVn4ZofJRiI0=",
    "VersionHash": "r5yH8hwGPQGpp+s7MTm+GpVd4TA="
  },
  "-33,-33": {
    "SourceVersionHash": "PjFa6jxycfFw/siKVn4ZofJRiI0=",
    "VersionHash": "r5yH8hwGPQGpp+s7MTm+GpVd4TA="
  }
}