{
  "31,71": {
    "SourceVersionHash": "jWFirZv2BZGdUSk9pDNpFbhe8vQ=",
    "VersionHash": "K5nuvUux9HafO9tBefRTjkN5GsI="
  },
  "30,71": {
    "SourceVersionHash": "jWFirZv2BZGdUSk9pDNpFbhe8vQ=",
    "VersionHash": "K5nuvUux9HafO9tBefRTjkN5GsI="
  },
  "29,71": {
    "SourceVersionHash": "jWFirZv2BZGdUSk9pDNpFbhe8vQ=",
    "VersionHash": "K5nuvUux9HafO9tBefRTjkN5GsI="
  },
  "28,71": {
    "SourceVersionHash": "jWFirZv2BZGdUSk9pDNpFbhe8vQ=",
    "VersionHash": "K5nuvUux9HafO9tBefRTjkN5GsI="
  },
  "27,71": {
    "SourceVersionHash": "jWFirZv2BZGdUSk9pDNpFbhe8vQ=",
    "VersionHash": "K5nuvUux9HafO9tBefRTjkN5GsI="
  },
  "26,71": {
    "SourceVersionHash": "jWFirZv2BZGdUSk9pDNpFbhe8vQ=",
    "VersionHash": "K5nuvUux9HafO9tBefRTjkN5GsI="
  },
  "25,71": {
    "SourceVersionHash": "jWFirZv2BZGdUSk9pDNpFbhe8vQ=",
    "VersionHash": "K5nuvUux9HafO9tBefRTjkN5GsI="
  },
  "31,70": {
    "SourceVersionHash": "jWFirZv2BZGdUSk9pDNpFbhe8vQ=",
    "VersionHash": "K5nuvUux9HafO9tBefRTjkN5GsI="
  },
  "30,70": {
    "SourceVersionHash": "jWFirZv2BZGdUSk9pDNpFbhe8vQ=",
    "VersionHash": "K5nuvUux9HafO9tBefRTjkN5GsI="
  },
  "29,70": {
    "SourceVersionHash": "jWFirZv2BZGdUSk9pDNpFbhe8vQ=",
    "VersionHash": "K5nuvUux9HafO9tBefRTjkN5GsI="
  },
  "28,70": {
    "SourceVersionHash": "jWFirZv2BZGdUSk9pDNpFbhe8vQ=",
    "VersionHash": "K5nuvUux9HafO9tBefRTjkN5GsI="
  },
  "27,70": {
    "SourceVersionHash": "jWFirZv2BZGdUSk9pDNpFbhe8vQ=",
    "VersionHash": "K5nuvUux9HafO9tBefRTjkN5GsI="
  },
  "26,70": {
    "SourceVersionHash": "jWFirZv2BZGdUSk9pDNpFbhe8vQ=",
    "VersionHash": "K5nuvUux9HafO9tBefRTjkN5GsI="
  },
  "25,70": {
    "SourceVersionHash": "jWFirZv2BZGdUSk9pDNpFbhe8vQ=",
    "VersionHash": "K5nuvUux9HafO9tBefRTjkN5GsI="
  },
  "31,69": {
    "SourceVersionHash": "jWFirZv2BZGdUSk9pDNpFbhe8vQ=",
    "VersionHash": "K5nuvUux9HafO9tBefRTjkN5GsI="
  },
  "30,69": {
    "SourceVersionHash": "jWFirZv2BZGdUSk9pDNpFbhe8vQ=",
    "VersionHash": "K5nuvUux9HafO9tBefRTjkN5GsI="
  },
  "29,69": {
    "SourceVersionHash": "jWFirZv2BZGdUSk9pDNpFbhe8vQ=",
    "VersionHash": "K5nuvUux9HafO9tBefRTjkN5GsI="
  },
  "28,69": {
    "SourceVersionHash": "jWFirZv2BZGdUSk9pDNpFbhe8vQ=",
    "VersionHash": "K5nuvUux9HafO9tBefRTjkN5GsI="
  },
  "27,69": {
    "SourceVersionHash": "jWFirZv2BZGdUSk9pDNpFbhe8vQ=",
    "VersionHash": "K5nuvUux9HafO9tBefRTjkN5GsI="
  },
  "26,69": {
    "SourceVersionHash": "jWFirZv2BZGdUSk9pDNpFbhe8vQ=",
    "VersionHash": "K5nuvUux9HafO9tBefRTjkN5GsI="
  },
  "25,69": {
    "SourceVersionHash": "jWFirZv2BZGdUSk9pDNpFbhe8vQ=",
    "VersionHash": "K5nuvUux9HafO9tBefRTjkN5GsI="
  },
  "31,68": {
    "SourceVersionHash": "jWFirZv2BZGdUSk9pDNpFbhe8vQ=",
    "VersionHash": "K5nuvUux9HafO9tBefRTjkN5GsI="
  },
  "30,68": {
    "SourceVersionHash": "jWFirZv2BZGdUSk9pDNpFbhe8vQ=",
    "VersionHash": "K5nuvUux9HafO9tBefRTjkN5GsI="
  },
  "29,68": {
    "SourceVersionHash": "jWFirZv2BZGdUSk9pDNpFbhe8vQ=",
    "VersionHash": "K5nuvUux9HafO9tBefRTjkN5GsI="
  },
  "28,68": {
    "SourceVersionHash": "jWFirZv2BZGdUSk9pDNpFbhe8vQ=",
    "VersionHash": "K5nuvUux9HafO9tBefRTjkN5GsI="
  },
  "25,65": {
    "SourceVersionHash": "jWFirZv2BZGdUSk9pDNpFbhe8vQ=",
    "VersionHash": "K5nuvUux9HafO9tBefRTjkN5GsI="
  },
  "27,68": {
    "SourceVersionHash": "jWFirZv2BZGdUSk9pDNpFbhe8vQ=",
    "VersionHash": "K5nuvUux9HafO9tBefRTjkN5GsI="
  },
  "26,68": {
    "SourceVersionHash": "jWFirZv2BZGdUSk9pDNpFbhe8vQ=",
    "VersionHash": "K5nuvUux9HafO9tBefRTjkN5GsI="
  },
  "25,68": {
    "SourceVersionHash": "jWFirZv2BZGdUSk9pDNpFbhe8vQ=",
    "VersionHash": "K5nuvUux9HafO9tBefRTjkN5GsI="
  },
  "31,67": {
    "SourceVersionHash": "jWFirZv2BZGdUSk9pDNpFbhe8vQ=",
    "VersionHash": "K5nuvUux9HafO9tBefRTjkN5GsI="
  },
  "30,67": {
    "SourceVersionHash": "jWFirZv2BZGdUSk9pDNpFbhe8vQ=",
    "VersionHash": "K5nuvUux9HafO9tBefRTjkN5GsI="
  },
  "29,67": {
    "SourceVersionHash": "jWFirZv2BZGdUSk9pDNpFbhe8vQ=",
    "VersionHash": "K5nuvUux9HafO9tBefRTjkN5GsI="
  },
  "28,67": {
    "SourceVersionHash": "jWFirZv2BZGdUSk9pDNpFbhe8vQ=",
    "VersionHash": "K5nuvUux9HafO9tBefRTjkN5GsI="
  },
  "27,67": {
    "SourceVersionHash": "jWFirZv2BZGdUSk9pDNpFbhe8vQ=",
    "VersionHash": "K5nuvUux9HafO9tBefRTjkN5GsI="
  },
  "26,67": {
    "SourceVersionHash": "jWFirZv2BZGdUSk9pDNpFbhe8vQ=",
    "VersionHash": "K5nuvUux9HafO9tBefRTjkN5GsI="
  },
  "25,67": {
    "SourceVersionHash": "jWFirZv2BZGdUSk9pDNpFbhe8vQ=",
    "VersionHash": "K5nuvUux9HafO9tBefRTjkN5GsI="
  },
  "31,66": {
    "SourceVersionHash": "jWFirZv2BZGdUSk9pDNpFbhe8vQ=",
    "VersionHash": "K5nuvUux9HafO9tBefRTjkN5GsI="
  },
  "30,66": {
    "SourceVersionHash": "jWFirZv2BZGdUSk9pDNpFbhe8vQ=",
    "VersionHash": "K5nuvUux9HafO9tBefRTjkN5GsI="
  },
  "29,66": {
    "SourceVersionHash": "jWFirZv2BZGdUSk9pDNpFbhe8vQ=",
    "VersionHash": "K5nuvUux9HafO9tBefRTjkN5GsI="
  },
  "28,66": {
    "SourceVersionHash": "jWFirZv2BZGdUSk9pDNpFbhe8vQ=",
    "VersionHash": "K5nuvUux9HafO9tBefRTjkN5GsI="
  },
  "27,65": {
    "SourceVersionHash": "jWFirZv2BZGdUSk9pDNpFbhe8vQ=",
    "VersionHash": "K5nuvUux9HafO9tBefRTjkN5GsI="
  },
  "28,65": {
    "SourceVersionHash": "jWFirZv2BZGdUSk9pDNpFbhe8vQ=",
    "VersionHash": "K5nuvUux9HafO9tBefRTjkN5GsI="
  },
  "26,65": {
    "SourceVersionHash": "jWFirZv2BZGdUSk9pDNpFbhe8vQ=",
    "VersionHash": "K5nuvUux9HafO9tBefRTjkN5GsI="
  },
  "27,66": {
    "SourceVersionHash": "jWFirZv2BZGdUSk9pDNpFbhe8vQ=",
    "VersionHash": "K5nuvUux9HafO9tBefRTjkN5GsI="
  },
  "31,64": {
    "SourceVersionHash": "jWFirZv2BZGdUSk9pDNpFbhe8vQ=",
    "VersionHash": "K5nuvUux9HafO9tBefRTjkN5GsI="
  },
  "30,64": {
    "SourceVersionHash": "jWFirZv2BZGdUSk9pDNpFbhe8vQ=",
    "VersionHash": "K5nuvUux9HafO9tBefRTjkN5GsI="
  },
  "26,66": {
    "SourceVersionHash": "jWFirZv2BZGdUSk9pDNpFbhe8vQ=",
    "VersionHash": "K5nuvUux9HafO9tBefRTjkN5GsI="
  },
  "29,64": {
    "SourceVersionHash": "jWFirZv2BZGdUSk9pDNpFbhe8vQ=",
    "VersionHash": "K5nuvUux9HafO9tBefRTjkN5GsI="
  },
  "25,66": {
    "SourceVersionHash": "jWFirZv2BZGdUSk9pDNpFbhe8vQ=",
    "VersionHash": "K5nuvUux9HafO9tBefRTjkN5GsI="
  },
  "28,64": {
    "SourceVersionHash": "jWFirZv2BZGdUSk9pDNpFbhe8vQ=",
    "VersionHash": "K5nuvUux9HafO9tBefRTjkN5GsI="
  },
  "31,65": {
    "SourceVersionHash": "jWFirZv2BZGdUSk9pDNpFbhe8vQ=",
    "VersionHash": "K5nuvUux9HafO9tBefRTjkN5GsI="
  },
  "27,64": {
    "SourceVersionHash": "jWFirZv2BZGdUSk9pDNpFbhe8vQ=",
    "VersionHash": "K5nuvUux9HafO9tBefRTjkN5GsI="
  },
  "30,65": {
    "SourceVersionHash": "jWFirZv2BZGdUSk9pDNpFbhe8vQ=",
    "VersionHash": "K5nuvUux9HafO9tBefRTjkN5GsI="
  },
  "26,64": {
    "SourceVersionHash": "jWFirZv2BZGdUSk9pDNpFbhe8vQ=",
    "VersionHash": "K5nuvUux9HafO9tBefRTjkN5GsI="
  },
  "29,65": {
    "SourceVersionHash": "jWFirZv2BZGdUSk9pDNpFbhe8vQ=",
    "VersionHash": "K5nuvUux9HafO9tBefRTjkN5GsI="
  },
  "25,64": {
    "SourceVersionHash": "jWFirZv2BZGdUSk9pDNpFbhe8vQ=",
    "VersionHash": "K5nuvUux9HafO9tBefRTjkN5GsI="
  },
  "6,71": {
    "SourceVersionHash": "PlURzimW96Cle+TNVvOKqJmdYkQ=",
    "VersionHash": "JYAkFOKQ/TaulASRBlaijDlrJLM="
  },
  "24,71": {
    "SourceVersionHash": "jWFirZv2BZGdUSk9pDNpFbhe8vQ=",
    "VersionHash": "JYAkFOKQ/TaulASRBlaijDlrJLM="
  },
  "5,71": {
    "SourceVersionHash": "PlURzimW96Cle+TNVvOKqJmdYkQ=",
    "VersionHash": "JYAkFOKQ/TaulASRBlaijDlrJLM="
  },
  "23,71": {
    "SourceVersionHash": "iQ/+oerXTV9RInXtlauTg30TuvQ=",
    "VersionHash": "JYAkFOKQ/TaulASRBlaijDlrJLM="
  },
  "4,71": {
    "SourceVersionHash": "PlURzimW96Cle+TNVvOKqJmdYkQ=",
    "VersionHash": "JYAkFOKQ/TaulASRBlaijDlrJLM="
  },
  "22,71": {
    "SourceVersionHash": "iQ/+oerXTV9RInXtlauTg30TuvQ=",
    "VersionHash": "JYAkFOKQ/TaulASRBlaijDlrJLM="
  },
  "3,71": {
    "SourceVersionHash": "PlURzimW96Cle+TNVvOKqJmdYkQ=",
    "VersionHash": "JYAkFOKQ/TaulASRBlaijDlrJLM="
  },
  "21,71": {
    "SourceVersionHash": "iQ/+oerXTV9RInXtlauTg30TuvQ=",
    "VersionHash": "JYAkFOKQ/TaulASRBlaijDlrJLM="
  },
  "2,71": {
    "SourceVersionHash": "PlURzimW96Cle+TNVvOKqJmdYkQ=",
    "VersionHash": "JYAkFOKQ/TaulASRBlaijDlrJLM="
  },
  "1,71": {
    "SourceVersionHash": "PlURzimW96Cle+TNVvOKqJmdYkQ=",
    "VersionHash": "JYAkFOKQ/TaulASRBlaijDlrJLM="
  },
  "0,71": {
    "SourceVersionHash": "PlURzimW96Cle+TNVvOKqJmdYkQ=",
    "VersionHash": "JYAkFOKQ/TaulASRBlaijDlrJLM="
  },
  "6,70": {
    "SourceVersionHash": "PlURzimW96Cle+TNVvOKqJmdYkQ=",
    "VersionHash": "JYAkFOKQ/TaulASRBlaijDlrJLM="
  },
  "5,70": {
    "SourceVersionHash": "PlURzimW96Cle+TNVvOKqJmdYkQ=",
    "VersionHash": "JYAkFOKQ/TaulASRBlaijDlrJLM="
  },
  "4,70": {
    "SourceVersionHash": "PlURzimW96Cle+TNVvOKqJmdYkQ=",
    "VersionHash": "JYAkFOKQ/TaulASRBlaijDlrJLM="
  },
  "3,70": {
    "SourceVersionHash": "PlURzimW96Cle+TNVvOKqJmdYkQ=",
    "VersionHash": "JYAkFOKQ/TaulASRBlaijDlrJLM="
  },
  "2,70": {
    "SourceVersionHash": "PlURzimW96Cle+TNVvOKqJmdYkQ=",
    "VersionHash": "JYAkFOKQ/TaulASRBlaijDlrJLM="
  },
  "1,70": {
    "SourceVersionHash": "PlURzimW96Cle+TNVvOKqJmdYkQ=",
    "VersionHash": "JYAkFOKQ/TaulASRBlaijDlrJLM="
  },
  "20,71": {
    "SourceVersionHash": "iQ/+oerXTV9RInXtlauTg30TuvQ=",
    "VersionHash": "JYAkFOKQ/TaulASRBlaijDlrJLM="
  },
  "19,71": {
    "SourceVersionHash": "iQ/+oerXTV9RInXtlauTg30TuvQ=",
    "VersionHash": "JYAkFOKQ/TaulASRBlaijDlrJLM="
  },
  "18,71": {
    "SourceVersionHash": "iQ/+oerXTV9RInXtlauTg30TuvQ=",
    "VersionHash": "JYAkFOKQ/TaulASRBlaijDlrJLM="
  },
  "17,71": {
    "SourceVersionHash": "iQ/+oerXTV9RInXtlauTg30TuvQ=",
    "VersionHash": "JYAkFOKQ/TaulASRBlaijDlrJLM="
  },
  "24,70": {
    "SourceVersionHash": "jWFirZv2BZGdUSk9pDNpFbhe8vQ=",
    "VersionHash": "JYAkFOKQ/TaulASRBlaijDlrJLM="
  },
  "23,70": {
    "SourceVersionHash": "iQ/+oerXTV9RInXtlauTg30TuvQ=",
    "VersionHash": "JYAkFOKQ/TaulASRBlaijDlrJLM="
  },
  "0,70": {
    "SourceVersionHash": "PlURzimW96Cle+TNVvOKqJmdYkQ=",
    "VersionHash": "JYAkFOKQ/TaulASRBlaijDlrJLM="
  },
  "22,70": {
    "SourceVersionHash": "iQ/+oerXTV9RInXtlauTg30TuvQ=",
    "VersionHash": "JYAkFOKQ/TaulASRBlaijDlrJLM="
  },
  "21,70": {
    "SourceVersionHash": "iQ/+oerXTV9RInXtlauTg30TuvQ=",
    "VersionHash": "JYAkFOKQ/TaulASRBlaijDlrJLM="
  },
  "6,65": {
    "SourceVersionHash": "PlURzimW96Cle+TNVvOKqJmdYkQ=",
    "VersionHash": "JYAkFOKQ/TaulASRBlaijDlrJLM="
  },
  "20,70": {
    "SourceVersionHash": "iQ/+oerXTV9RInXtlauTg30TuvQ=",
    "VersionHash": "JYAkFOKQ/TaulASRBlaijDlrJLM="
  },
  "1,65": {
    "SourceVersionHash": "PlURzimW96Cle+TNVvOKqJmdYkQ=",
    "VersionHash": "JYAkFOKQ/TaulASRBlaijDlrJLM="
  },
  "4,65": {
    "SourceVersionHash": "PlURzimW96Cle+TNVvOKqJmdYkQ=",
    "VersionHash": "JYAkFOKQ/TaulASRBlaijDlrJLM="
  },
  "0,65": {
    "SourceVersionHash": "PlURzimW96Cle+TNVvOKqJmdYkQ=",
    "VersionHash": "JYAkFOKQ/TaulASRBlaijDlrJLM="
  },
  "6,69": {
    "SourceVersionHash": "PlURzimW96Cle+TNVvOKqJmdYkQ=",
    "VersionHash": "JYAkFOKQ/TaulASRBlaijDlrJLM="
  },
  "2,65": {
    "SourceVersionHash": "PlURzimW96Cle+TNVvOKqJmdYkQ=",
    "VersionHash": "JYAkFOKQ/TaulASRBlaijDlrJLM="
  },
  "5,69": {
    "SourceVersionHash": "PlURzimW96Cle+TNVvOKqJmdYkQ=",
    "VersionHash": "JYAkFOKQ/TaulASRBlaijDlrJLM="
  },
  "5,65": {
    "SourceVersionHash": "PlURzimW96Cle+TNVvOKqJmdYkQ=",
    "VersionHash": "JYAkFOKQ/TaulASRBlaijDlrJLM="
  },
  "1,66": {
    "SourceVersionHash": "PlURzimW96Cle+TNVvOKqJmdYkQ=",
    "VersionHash": "JYAkFOKQ/TaulASRBlaijDlrJLM="
  },
  "19,65": {
    "SourceVersionHash": "iQ/+oerXTV9RInXtlauTg30TuvQ=",
    "VersionHash": "JYAkFOKQ/TaulASRBlaijDlrJLM="
  },
  "4,69": {
    "SourceVersionHash": "PlURzimW96Cle+TNVvOKqJmdYkQ=",
    "VersionHash": "JYAkFOKQ/TaulASRBlaijDlrJLM="
  },
  "17,65": {
    "SourceVersionHash": "iQ/+oerXTV9RInXtlauTg30TuvQ=",
    "VersionHash": "JYAkFOKQ/TaulASRBlaijDlrJLM="
  },
  "20,65": {
    "SourceVersionHash": "iQ/+oerXTV9RInXtlauTg30TuvQ=",
    "VersionHash": "JYAkFOKQ/TaulASRBlaijDlrJLM="
  },
  "3,65": {
    "SourceVersionHash": "PlURzimW96Cle+TNVvOKqJmdYkQ=",
    "VersionHash": "JYAkFOKQ/TaulASRBlaijDlrJLM="
  },
  "17,66": {
    "SourceVersionHash": "iQ/+oerXTV9RInXtlauTg30TuvQ=",
    "VersionHash": "JYAkFOKQ/TaulASRBlaijDlrJLM="
  },
  "5,66": {
    "SourceVersionHash": "PlURzimW96Cle+TNVvOKqJmdYkQ=",
    "VersionHash": "JYAkFOKQ/TaulASRBlaijDlrJLM="
  },
  "22,65": {
    "SourceVersionHash": "iQ/+oerXTV9RInXtlauTg30TuvQ=",
    "VersionHash": "JYAkFOKQ/TaulASRBlaijDlrJLM="
  },
  "3,66": {
    "SourceVersionHash": "PlURzimW96Cle+TNVvOKqJmdYkQ=",
    "VersionHash": "JYAkFOKQ/TaulASRBlaijDlrJLM="
  },
  "21,65": {
    "SourceVersionHash": "iQ/+oerXTV9RInXtlauTg30TuvQ=",
    "VersionHash": "JYAkFOKQ/TaulASRBlaijDlrJLM="
  },
  "23,65": {
    "SourceVersionHash": "iQ/+oerXTV9RInXtlauTg30TuvQ=",
    "VersionHash": "JYAkFOKQ/TaulASRBlaijDlrJLM="
  },
  "19,70": {
    "SourceVersionHash": "iQ/+oerXTV9RInXtlauTg30TuvQ=",
    "VersionHash": "JYAkFOKQ/TaulASRBlaijDlrJLM="
  },
  "21,66": {
    "SourceVersionHash": "iQ/+oerXTV9RInXtlauTg30TuvQ=",
    "VersionHash": "JYAkFOKQ/TaulASRBlaijDlrJLM="
  },
  "20,66": {
    "SourceVersionHash": "iQ/+oerXTV9RInXtlauTg30TuvQ=",
    "VersionHash": "JYAkFOKQ/TaulASRBlaijDlrJLM="
  },
  "0,66": {
    "SourceVersionHash": "PlURzimW96Cle+TNVvOKqJmdYkQ=",
    "VersionHash": "JYAkFOKQ/TaulASRBlaijDlrJLM="
  },
  "4,66": {
    "SourceVersionHash": "PlURzimW96Cle+TNVvOKqJmdYkQ=",
    "VersionHash": "JYAkFOKQ/TaulASRBlaijDlrJLM="
  },
  "18,70": {
    "SourceVersionHash": "iQ/+oerXTV9RInXtlauTg30TuvQ=",
    "VersionHash": "JYAkFOKQ/TaulASRBlaijDlrJLM="
  },
  "24,65": {
    "SourceVersionHash": "jWFirZv2BZGdUSk9pDNpFbhe8vQ=",
    "VersionHash": "JYAkFOKQ/TaulASRBlaijDlrJLM="
  },
  "18,65": {
    "SourceVersionHash": "iQ/+oerXTV9RInXtlauTg30TuvQ=",
    "VersionHash": "JYAkFOKQ/TaulASRBlaijDlrJLM="
  },
  "2,66": {
    "SourceVersionHash": "PlURzimW96Cle+TNVvOKqJmdYkQ=",
    "VersionHash": "JYAkFOKQ/TaulASRBlaijDlrJLM="
  },
  "19,66": {
    "SourceVersionHash": "iQ/+oerXTV9RInXtlauTg30TuvQ=",
    "VersionHash": "JYAkFOKQ/TaulASRBlaijDlrJLM="
  },
  "3,69": {
    "SourceVersionHash": "PlURzimW96Cle+TNVvOKqJmdYkQ=",
    "VersionHash": "JYAkFOKQ/TaulASRBlaijDlrJLM="
  },
  "1,67": {
    "SourceVersionHash": "PlURzimW96Cle+TNVvOKqJmdYkQ=",
    "VersionHash": "JYAkFOKQ/TaulASRBlaijDlrJLM="
  },
  "0,67": {
    "SourceVersionHash": "PlURzimW96Cle+TNVvOKqJmdYkQ=",
    "VersionHash": "JYAkFOKQ/TaulASRBlaijDlrJLM="
  },
  "18,66": {
    "SourceVersionHash": "iQ/+oerXTV9RInXtlauTg30TuvQ=",
    "VersionHash": "JYAkFOKQ/TaulASRBlaijDlrJLM="
  },
  "2,69": {
    "SourceVersionHash": "PlURzimW96Cle+TNVvOKqJmdYkQ=",
    "VersionHash": "JYAkFOKQ/TaulASRBlaijDlrJLM="
  },
  "17,70": {
    "SourceVersionHash": "iQ/+oerXTV9RInXtlauTg30TuvQ=",
    "VersionHash": "JYAkFOKQ/TaulASRBlaijDlrJLM="
  },
  "2,67": {
    "SourceVersionHash": "PlURzimW96Cle+TNVvOKqJmdYkQ=",
    "VersionHash": "JYAkFOKQ/TaulASRBlaijDlrJLM="
  },
  "19,69": {
    "SourceVersionHash": "iQ/+oerXTV9RInXtlauTg30TuvQ=",
    "VersionHash": "JYAkFOKQ/TaulASRBlaijDlrJLM="
  },
  "18,69": {
    "SourceVersionHash": "iQ/+oerXTV9RInXtlauTg30TuvQ=",
    "VersionHash": "JYAkFOKQ/TaulASRBlaijDlrJLM="
  },
  "23,69": {
    "SourceVersionHash": "iQ/+oerXTV9RInXtlauTg30TuvQ=",
    "VersionHash": "JYAkFOKQ/TaulASRBlaijDlrJLM="
  },
  "1,69": {
    "SourceVersionHash": "PlURzimW96Cle+TNVvOKqJmdYkQ=",
    "VersionHash": "JYAkFOKQ/TaulASRBlaijDlrJLM="
  },
  "17,69": {
    "SourceVersionHash": "iQ/+oerXTV9RInXtlauTg30TuvQ=",
    "VersionHash": "JYAkFOKQ/TaulASRBlaijDlrJLM="
  },
  "22,69": {
    "SourceVersionHash": "iQ/+oerXTV9RInXtlauTg30TuvQ=",
    "VersionHash": "JYAkFOKQ/TaulASRBlaijDlrJLM="
  },
  "6,66": {
    "SourceVersionHash": "PlURzimW96Cle+TNVvOKqJmdYkQ=",
    "VersionHash": "JYAkFOKQ/TaulASRBlaijDlrJLM="
  },
  "24,69": {
    "SourceVersionHash": "jWFirZv2BZGdUSk9pDNpFbhe8vQ=",
    "VersionHash": "JYAkFOKQ/TaulASRBlaijDlrJLM="
  },
  "21,69": {
    "SourceVersionHash": "iQ/+oerXTV9RInXtlauTg30TuvQ=",
    "VersionHash": "JYAkFOKQ/TaulASRBlaijDlrJLM="
  },
  "21,68": {
    "SourceVersionHash": "iQ/+oerXTV9RInXtlauTg30TuvQ=",
    "VersionHash": "JYAkFOKQ/TaulASRBlaijDlrJLM="
  },
  "22,68": {
    "SourceVersionHash": "iQ/+oerXTV9RInXtlauTg30TuvQ=",
    "VersionHash": "JYAkFOKQ/TaulASRBlaijDlrJLM="
  },
  "23,68": {
    "SourceVersionHash": "iQ/+oerXTV9RInXtlauTg30TuvQ=",
    "VersionHash": "JYAkFOKQ/TaulASRBlaijDlrJLM="
  },
  "20,69": {
    "SourceVersionHash": "iQ/+oerXTV9RInXtlauTg30TuvQ=",
    "VersionHash": "JYAkFOKQ/TaulASRBlaijDlrJLM="
  },
  "18,68": {
    "SourceVersionHash": "iQ/+oerXTV9RInXtlauTg30TuvQ=",
    "VersionHash": "JYAkFOKQ/TaulASRBlaijDlrJLM="
  },
  "0,69": {
    "SourceVersionHash": "PlURzimW96Cle+TNVvOKqJmdYkQ=",
    "VersionHash": "JYAkFOKQ/TaulASRBlaijDlrJLM="
  },
  "19,68": {
    "SourceVersionHash": "iQ/+oerXTV9RInXtlauTg30TuvQ=",
    "VersionHash": "JYAkFOKQ/TaulASRBlaijDlrJLM="
  },
  "20,68": {
    "SourceVersionHash": "iQ/+oerXTV9RInXtlauTg30TuvQ=",
    "VersionHash": "JYAkFOKQ/TaulASRBlaijDlrJLM="
  },
  "17,68": {
    "SourceVersionHash": "iQ/+oerXTV9RInXtlauTg30TuvQ=",
    "VersionHash": "JYAkFOKQ/TaulASRBlaijDlrJLM="
  },
  "24,68": {
    "SourceVersionHash": "jWFirZv2BZGdUSk9pDNpFbhe8vQ=",
    "VersionHash": "JYAkFOKQ/TaulASRBlaijDlrJLM="
  },
  "24,67": {
    "SourceVersionHash": "jWFirZv2BZGdUSk9pDNpFbhe8vQ=",
    "VersionHash": "JYAkFOKQ/TaulASRBlaijDlrJLM="
  },
  "18,67": {
    "SourceVersionHash": "iQ/+oerXTV9RInXtlauTg30TuvQ=",
    "VersionHash": "JYAkFOKQ/TaulASRBlaijDlrJLM="
  },
  "19,67": {
    "SourceVersionHash": "iQ/+oerXTV9RInXtlauTg30TuvQ=",
    "VersionHash": "JYAkFOKQ/TaulASRBlaijDlrJLM="
  },
  "17,67": {
    "SourceVersionHash": "iQ/+oerXTV9RInXtlauTg30TuvQ=",
    "VersionHash": "JYAkFOKQ/TaulASRBlaijDlrJLM="
  },
  "21,67": {
    "SourceVersionHash": "iQ/+oerXTV9RInXtlauTg30TuvQ=",
    "VersionHash": "JYAkFOKQ/TaulASRBlaijDlrJLM="
  },
  "23,67": {
    "SourceVersionHash": "iQ/+oerXTV9RInXtlauTg30TuvQ=",
    "VersionHash": "JYAkFOKQ/TaulASRBlaijDlrJLM="
  },
  "6,68": {
    "SourceVersionHash": "PlURzimW96Cle+TNVvOKqJmdYkQ=",
    "VersionHash": "JYAkFOKQ/TaulASRBlaijDlrJLM="
  },
  "23,66": {
    "SourceVersionHash": "iQ/+oerXTV9RInXtlauTg30TuvQ=",
    "VersionHash": "JYAkFOKQ/TaulASRBlaijDlrJLM="
  },
  "16,71": {
    "SourceVersionHash": "iQ/+oerXTV9RInXtlauTg30TuvQ=",
    "VersionHash": "JYAkFOKQ/TaulASRBlaijDlrJLM="
  },
  "5,68": {
    "SourceVersionHash": "PlURzimW96Cle+TNVvOKqJmdYkQ=",
    "VersionHash": "JYAkFOKQ/TaulASRBlaijDlrJLM="
  },
  "24,66": {
    "SourceVersionHash": "jWFirZv2BZGdUSk9pDNpFbhe8vQ=",
    "VersionHash": "JYAkFOKQ/TaulASRBlaijDlrJLM="
  },
  "15,71": {
    "SourceVersionHash": "e3exm8NTn7dchXOM1ME3TpXE04U=",
    "VersionHash": "JYAkFOKQ/TaulASRBlaijDlrJLM="
  },
  "20,67": {
    "SourceVersionHash": "iQ/+oerXTV9RInXtlauTg30TuvQ=",
    "VersionHash": "JYAkFOKQ/TaulASRBlaijDlrJLM="
  },
  "22,66": {
    "SourceVersionHash": "iQ/+oerXTV9RInXtlauTg30TuvQ=",
    "VersionHash": "JYAkFOKQ/TaulASRBlaijDlrJLM="
  },
  "22,67": {
    "SourceVersionHash": "iQ/+oerXTV9RInXtlauTg30TuvQ=",
    "VersionHash": "JYAkFOKQ/TaulASRBlaijDlrJLM="
  },
  "14,71": {
    "SourceVersionHash": "e3exm8NTn7dchXOM1ME3TpXE04U=",
    "VersionHash": "JYAkFOKQ/TaulASRBlaijDlrJLM="
  },
  "4,68": {
    "SourceVersionHash": "PlURzimW96Cle+TNVvOKqJmdYkQ=",
    "VersionHash": "JYAkFOKQ/TaulASRBlaijDlrJLM="
  },
  "5,67": {
    "SourceVersionHash": "PlURzimW96Cle+TNVvOKqJmdYkQ=",
    "VersionHash": "JYAkFOKQ/TaulASRBlaijDlrJLM="
  },
  "3,67": {
    "SourceVersionHash": "PlURzimW96Cle+TNVvOKqJmdYkQ=",
    "VersionHash": "JYAkFOKQ/TaulASRBlaijDlrJLM="
  },
  "13,71": {
    "SourceVersionHash": "e3exm8NTn7dchXOM1ME3TpXE04U=",
    "VersionHash": "JYAkFOKQ/TaulASRBlaijDlrJLM="
  },
  "3,68": {
    "SourceVersionHash": "PlURzimW96Cle+TNVvOKqJmdYkQ=",
    "VersionHash": "JYAkFOKQ/TaulASRBlaijDlrJLM="
  },
  "7,65": {
    "SourceVersionHash": "PlURzimW96Cle+TNVvOKqJmdYkQ=",
    "VersionHash": "JYAkFOKQ/TaulASRBlaijDlrJLM="
  },
  "4,67": {
    "SourceVersionHash": "PlURzimW96Cle+TNVvOKqJmdYkQ=",
    "VersionHash": "JYAkFOKQ/TaulASRBlaijDlrJLM="
  },
  "12,71": {
    "SourceVersionHash": "e3exm8NTn7dchXOM1ME3TpXE04U=",
    "VersionHash": "JYAkFOKQ/TaulASRBlaijDlrJLM="
  },
  "2,68": {
    "SourceVersionHash": "PlURzimW96Cle+TNVvOKqJmdYkQ=",
    "VersionHash": "JYAkFOKQ/TaulASRBlaijDlrJLM="
  },
  "11,71": {
    "SourceVersionHash": "e3exm8NTn7dchXOM1ME3TpXE04U=",
    "VersionHash": "JYAkFOKQ/TaulASRBlaijDlrJLM="
  },
  "1,68": {
    "SourceVersionHash": "PlURzimW96Cle+TNVvOKqJmdYkQ=",
    "VersionHash": "JYAkFOKQ/TaulASRBlaijDlrJLM="
  },
  "10,71": {
    "SourceVersionHash": "e3exm8NTn7dchXOM1ME3TpXE04U=",
    "VersionHash": "JYAkFOKQ/TaulASRBlaijDlrJLM="
  },
  "0,68": {
    "SourceVersionHash": "PlURzimW96Cle+TNVvOKqJmdYkQ=",
    "VersionHash": "JYAkFOKQ/TaulASRBlaijDlrJLM="
  },
  "9,71": {
    "SourceVersionHash": "e3exm8NTn7dchXOM1ME3TpXE04U=",
    "VersionHash": "JYAkFOKQ/TaulASRBlaijDlrJLM="
  },
  "8,71": {
    "SourceVersionHash": "e3exm8NTn7dchXOM1ME3TpXE04U=",
    "VersionHash": "JYAkFOKQ/TaulASRBlaijDlrJLM="
  },
  "6,67": {
    "SourceVersionHash": "PlURzimW96Cle+TNVvOKqJmdYkQ=",
    "VersionHash": "JYAkFOKQ/TaulASRBlaijDlrJLM="
  },
  "7,71": {
    "SourceVersionHash": "PlURzimW96Cle+TNVvOKqJmdYkQ=",
    "VersionHash": "JYAkFOKQ/TaulASRBlaijDlrJLM="
  },
  "16,70": {
    "SourceVersionHash": "iQ/+oerXTV9RInXtlauTg30TuvQ=",
    "VersionHash": "JYAkFOKQ/TaulASRBlaijDlrJLM="
  },
  "15,70": {
    "SourceVersionHash": "e3exm8NTn7dchXOM1ME3TpXE04U=",
    "VersionHash": "JYAkFOKQ/TaulASRBlaijDlrJLM="
  },
  "10,65": {
    "SourceVersionHash": "e3exm8NTn7dchXOM1ME3TpXE04U=",
    "VersionHash": "JYAkFOKQ/TaulASRBlaijDlrJLM="
  },
  "9,65": {
    "SourceVersionHash": "e3exm8NTn7dchXOM1ME3TpXE04U=",
    "VersionHash": "JYAkFOKQ/TaulASRBlaijDlrJLM="
  },
  "13,65": {
    "SourceVersionHash": "e3exm8NTn7dchXOM1ME3TpXE04U=",
    "VersionHash": "JYAkFOKQ/TaulASRBlaijDlrJLM="
  },
  "14,70": {
    "SourceVersionHash": "e3exm8NTn7dchXOM1ME3TpXE04U=",
    "VersionHash": "JYAkFOKQ/TaulASRBlaijDlrJLM="
  },
  "13,70": {
    "SourceVersionHash": "e3exm8NTn7dchXOM1ME3TpXE04U=",
    "VersionHash": "JYAkFOKQ/TaulASRBlaijDlrJLM="
  },
  "12,65": {
    "SourceVersionHash": "e3exm8NTn7dchXOM1ME3TpXE04U=",
    "VersionHash": "JYAkFOKQ/TaulASRBlaijDlrJLM="
  },
  "12,70": {
    "SourceVersionHash": "e3exm8NTn7dchXOM1ME3TpXE04U=",
    "VersionHash": "JYAkFOKQ/TaulASRBlaijDlrJLM="
  },
  "8,65": {
    "SourceVersionHash": "e3exm8NTn7dchXOM1ME3TpXE04U=",
    "VersionHash": "JYAkFOKQ/TaulASRBlaijDlrJLM="
  },
  "11,70": {
    "SourceVersionHash": "e3exm8NTn7dchXOM1ME3TpXE04U=",
    "VersionHash": "JYAkFOKQ/TaulASRBlaijDlrJLM="
  },
  "14,65": {
    "SourceVersionHash": "e3exm8NTn7dchXOM1ME3TpXE04U=",
    "VersionHash": "JYAkFOKQ/TaulASRBlaijDlrJLM="
  },
  "11,65": {
    "SourceVersionHash": "e3exm8NTn7dchXOM1ME3TpXE04U=",
    "VersionHash": "JYAkFOKQ/TaulASRBlaijDlrJLM="
  },
  "15,65": {
    "SourceVersionHash": "e3exm8NTn7dchXOM1ME3TpXE04U=",
    "VersionHash": "JYAkFOKQ/TaulASRBlaijDlrJLM="
  },
  "10,70": {
    "SourceVersionHash": "e3exm8NTn7dchXOM1ME3TpXE04U=",
    "VersionHash": "JYAkFOKQ/TaulASRBlaijDlrJLM="
  },
  "9,70": {
    "SourceVersionHash": "e3exm8NTn7dchXOM1ME3TpXE04U=",
    "VersionHash": "JYAkFOKQ/TaulASRBlaijDlrJLM="
  },
  "11,66": {
    "SourceVersionHash": "e3exm8NTn7dchXOM1ME3TpXE04U=",
    "VersionHash": "JYAkFOKQ/TaulASRBlaijDlrJLM="
  },
  "9,66": {
    "SourceVersionHash": "e3exm8NTn7dchXOM1ME3TpXE04U=",
    "VersionHash": "JYAkFOKQ/TaulASRBlaijDlrJLM="
  },
  "14,66": {
    "SourceVersionHash": "e3exm8NTn7dchXOM1ME3TpXE04U=",
    "VersionHash": "JYAkFOKQ/TaulASRBlaijDlrJLM="
  },
  "15,66": {
    "SourceVersionHash": "e3exm8NTn7dchXOM1ME3TpXE04U=",
    "VersionHash": "JYAkFOKQ/TaulASRBlaijDlrJLM="
  },
  "10,66": {
    "SourceVersionHash": "e3exm8NTn7dchXOM1ME3TpXE04U=",
    "VersionHash": "JYAkFOKQ/TaulASRBlaijDlrJLM="
  },
  "13,66": {
    "SourceVersionHash": "e3exm8NTn7dchXOM1ME3TpXE04U=",
    "VersionHash": "JYAkFOKQ/TaulASRBlaijDlrJLM="
  },
  "8,70": {
    "SourceVersionHash": "e3exm8NTn7dchXOM1ME3TpXE04U=",
    "VersionHash": "JYAkFOKQ/TaulASRBlaijDlrJLM="
  },
  "12,66": {
    "SourceVersionHash": "e3exm8NTn7dchXOM1ME3TpXE04U=",
    "VersionHash": "JYAkFOKQ/TaulASRBlaijDlrJLM="
  },
  "7,70": {
    "SourceVersionHash": "PlURzimW96Cle+TNVvOKqJmdYkQ=",
    "VersionHash": "JYAkFOKQ/TaulASRBlaijDlrJLM="
  },
  "7,66": {
    "SourceVersionHash": "PlURzimW96Cle+TNVvOKqJmdYkQ=",
    "VersionHash": "JYAkFOKQ/TaulASRBlaijDlrJLM="
  },
  "16,69": {
    "SourceVersionHash": "iQ/+oerXTV9RInXtlauTg30TuvQ=",
    "VersionHash": "JYAkFOKQ/TaulASRBlaijDlrJLM="
  },
  "8,66": {
    "SourceVersionHash": "e3exm8NTn7dchXOM1ME3TpXE04U=",
    "VersionHash": "JYAkFOKQ/TaulASRBlaijDlrJLM="
  },
  "15,69": {
    "SourceVersionHash": "e3exm8NTn7dchXOM1ME3TpXE04U=",
    "VersionHash": "JYAkFOKQ/TaulASRBlaijDlrJLM="
  },
  "14,69": {
    "SourceVersionHash": "e3exm8NTn7dchXOM1ME3TpXE04U=",
    "VersionHash": "JYAkFOKQ/TaulASRBlaijDlrJLM="
  },
  "16,65": {
    "SourceVersionHash": "iQ/+oerXTV9RInXtlauTg30TuvQ=",
    "VersionHash": "JYAkFOKQ/TaulASRBlaijDlrJLM="
  },
  "7,67": {
    "SourceVersionHash": "PlURzimW96Cle+TNVvOKqJmdYkQ=",
    "VersionHash": "JYAkFOKQ/TaulASRBlaijDlrJLM="
  },
  "8,67": {
    "SourceVersionHash": "e3exm8NTn7dchXOM1ME3TpXE04U=",
    "VersionHash": "JYAkFOKQ/TaulASRBlaijDlrJLM="
  },
  "10,67": {
    "SourceVersionHash": "e3exm8NTn7dchXOM1ME3TpXE04U=",
    "VersionHash": "JYAkFOKQ/TaulASRBlaijDlrJLM="
  },
  "9,67": {
    "SourceVersionHash": "e3exm8NTn7dchXOM1ME3TpXE04U=",
    "VersionHash": "JYAkFOKQ/TaulASRBlaijDlrJLM="
  },
  "16,66": {
    "SourceVersionHash": "iQ/+oerXTV9RInXtlauTg30TuvQ=",
    "VersionHash": "JYAkFOKQ/TaulASRBlaijDlrJLM="
  },
  "11,67": {
    "SourceVersionHash": "e3exm8NTn7dchXOM1ME3TpXE04U=",
    "VersionHash": "JYAkFOKQ/TaulASRBlaijDlrJLM="
  },
  "13,69": {
    "SourceVersionHash": "e3exm8NTn7dchXOM1ME3TpXE04U=",
    "VersionHash": "JYAkFOKQ/TaulASRBlaijDlrJLM="
  },
  "12,69": {
    "SourceVersionHash": "e3exm8NTn7dchXOM1ME3TpXE04U=",
    "VersionHash": "JYAkFOKQ/TaulASRBlaijDlrJLM="
  },
  "11,69": {
    "SourceVersionHash": "e3exm8NTn7dchXOM1ME3TpXE04U=",
    "VersionHash": "JYAkFOKQ/TaulASRBlaijDlrJLM="
  },
  "13,67": {
    "SourceVersionHash": "e3exm8NTn7dchXOM1ME3TpXE04U=",
    "VersionHash": "JYAkFOKQ/TaulASRBlaijDlrJLM="
  },
  "9,68": {
    "SourceVersionHash": "e3exm8NTn7dchXOM1ME3TpXE04U=",
    "VersionHash": "JYAkFOKQ/TaulASRBlaijDlrJLM="
  },
  "8,68": {
    "SourceVersionHash": "e3exm8NTn7dchXOM1ME3TpXE04U=",
    "VersionHash": "JYAkFOKQ/TaulASRBlaijDlrJLM="
  },
  "16,67": {
    "SourceVersionHash": "iQ/+oerXTV9RInXtlauTg30TuvQ=",
    "VersionHash": "JYAkFOKQ/TaulASRBlaijDlrJLM="
  },
  "7,68": {
    "SourceVersionHash": "PlURzimW96Cle+TNVvOKqJmdYkQ=",
    "VersionHash": "JYAkFOKQ/TaulASRBlaijDlrJLM="
  },
  "15,67": {
    "SourceVersionHash": "e3exm8NTn7dchXOM1ME3TpXE04U=",
    "VersionHash": "JYAkFOKQ/TaulASRBlaijDlrJLM="
  },
  "10,68": {
    "SourceVersionHash": "e3exm8NTn7dchXOM1ME3TpXE04U=",
    "VersionHash": "JYAkFOKQ/TaulASRBlaijDlrJLM="
  },
  "14,67": {
    "SourceVersionHash": "e3exm8NTn7dchXOM1ME3TpXE04U=",
    "VersionHash": "JYAkFOKQ/TaulASRBlaijDlrJLM="
  },
  "13,68": {
    "SourceVersionHash": "e3exm8NTn7dchXOM1ME3TpXE04U=",
    "VersionHash": "JYAkFOKQ/TaulASRBlaijDlrJLM="
  },
  "11,68": {
    "SourceVersionHash": "e3exm8NTn7dchXOM1ME3TpXE04U=",
    "VersionHash": "JYAkFOKQ/TaulASRBlaijDlrJLM="
  },
  "12,68": {
    "SourceVersionHash": "e3exm8NTn7dchXOM1ME3TpXE04U=",
    "VersionHash": "JYAkFOKQ/TaulASRBlaijDlrJLM="
  },
  "10,69": {
    "SourceVersionHash": "e3exm8NTn7dchXOM1ME3TpXE04U=",
    "VersionHash": "JYAkFOKQ/TaulASRBlaijDlrJLM="
  },
  "9,69": {
    "SourceVersionHash": "e3exm8NTn7dchXOM1ME3TpXE04U=",
    "VersionHash": "JYAkFOKQ/TaulASRBlaijDlrJLM="
  },
  "12,67": {
    "SourceVersionHash": "e3exm8NTn7dchXOM1ME3TpXE04U=",
    "VersionHash": "FHsTU9ZJpqlQiWc1y7LBDMdNuAw="
  },
  "8,69": {
    "SourceVersionHash": "e3exm8NTn7dchXOM1ME3TpXE04U=",
    "VersionHash": "FHsTU9ZJpqlQiWc1y7LBDMdNuAw="
  },
  "7,69": {
    "SourceVersionHash": "PlURzimW96Cle+TNVvOKqJmdYkQ=",
    "VersionHash": "FHsTU9ZJpqlQiWc1y7LBDMdNuAw="
  },
  "16,68": {
    "SourceVersionHash": "iQ/+oerXTV9RInXtlauTg30TuvQ=",
    "VersionHash": "FHsTU9ZJpqlQiWc1y7LBDMdNuAw="
  },
  "15,68": {
    "SourceVersionHash": "e3exm8NTn7dchXOM1ME3TpXE04U=",
    "VersionHash": "FHsTU9ZJpqlQiWc1y7LBDMdNuAw="
  },
  "14,68": {
    "SourceVersionHash": "e3exm8NTn7dchXOM1ME3TpXE04U=",
    "VersionHash": "FHsTU9ZJpqlQiWc1y7LBDMdNuAw="
  },
  "6,64": {
    "SourceVersionHash": "PlURzimW96Cle+TNVvOKqJmdYkQ=",
    "VersionHash": "FHsTU9ZJpqlQiWc1y7LBDMdNuAw="
  },
  "5,64": {
    "SourceVersionHash": "PlURzimW96Cle+TNVvOKqJmdYkQ=",
    "VersionHash": "FHsTU9ZJpqlQiWc1y7LBDMdNuAw="
  },
  "4,64": {
    "SourceVersionHash": "PlURzimW96Cle+TNVvOKqJmdYkQ=",
    "VersionHash": "FHsTU9ZJpqlQiWc1y7LBDMdNuAw="
  },
  "3,64": {
    "SourceVersionHash": "PlURzimW96Cle+TNVvOKqJmdYkQ=",
    "VersionHash": "FHsTU9ZJpqlQiWc1y7LBDMdNuAw="
  },
  "2,64": {
    "SourceVersionHash": "PlURzimW96Cle+TNVvOKqJmdYkQ=",
    "VersionHash": "FHsTU9ZJpqlQiWc1y7LBDMdNuAw="
  },
  "1,64": {
    "SourceVersionHash": "PlURzimW96Cle+TNVvOKqJmdYkQ=",
    "VersionHash": "FHsTU9ZJpqlQiWc1y7LBDMdNuAw="
  },
  "14,64": {
    "SourceVersionHash": "e3exm8NTn7dchXOM1ME3TpXE04U=",
    "VersionHash": "FHsTU9ZJpqlQiWc1y7LBDMdNuAw="
  },
  "13,64": {
    "SourceVersionHash": "e3exm8NTn7dchXOM1ME3TpXE04U=",
    "VersionHash": "FHsTU9ZJpqlQiWc1y7LBDMdNuAw="
  },
  "12,64": {
    "SourceVersionHash": "e3exm8NTn7dchXOM1ME3TpXE04U=",
    "VersionHash": "FHsTU9ZJpqlQiWc1y7LBDMdNuAw="
  },
  "11,64": {
    "SourceVersionHash": "e3exm8NTn7dchXOM1ME3TpXE04U=",
    "VersionHash": "FHsTU9ZJpqlQiWc1y7LBDMdNuAw="
  },
  "10,64": {
    "SourceVersionHash": "e3exm8NTn7dchXOM1ME3TpXE04U=",
    "VersionHash": "FHsTU9ZJpqlQiWc1y7LBDMdNuAw="
  },
  "9,64": {
    "SourceVersionHash": "e3exm8NTn7dchXOM1ME3TpXE04U=",
    "VersionHash": "FHsTU9ZJpqlQiWc1y7LBDMdNuAw="
  },
  "8,64": {
    "SourceVersionHash": "e3exm8NTn7dchXOM1ME3TpXE04U=",
    "VersionHash": "FHsTU9ZJpqlQiWc1y7LBDMdNuAw="
  },
  "7,64": {
    "SourceVersionHash": "PlURzimW96Cle+TNVvOKqJmdYkQ=",
    "VersionHash": "FHsTU9ZJpqlQiWc1y7LBDMdNuAw="
  },
  "0,64": {
    "SourceVersionHash": "PlURzimW96Cle+TNVvOKqJmdYkQ=",
    "VersionHash": "FHsTU9ZJpqlQiWc1y7LBDMdNuAw="
  },
  "24,64": {
    "SourceVersionHash": "jWFirZv2BZGdUSk9pDNpFbhe8vQ=",
    "VersionHash": "G/UvrA84lSiYex1/Vx7yOo42M1M="
  },
  "23,64": {
    "SourceVersionHash": "iQ/+oerXTV9RInXtlauTg30TuvQ=",
    "VersionHash": "G/UvrA84lSiYex1/Vx7yOo42M1M="
  },
  "22,64": {
    "SourceVersionHash": "iQ/+oerXTV9RInXtlauTg30TuvQ=",
    "VersionHash": "G/UvrA84lSiYex1/Vx7yOo42M1M="
  },
  "21,64": {
    "SourceVersionHash": "iQ/+oerXTV9RInXtlauTg30TuvQ=",
    "VersionHash": "G/UvrA84lSiYex1/Vx7yOo42M1M="
  },
  "20,64": {
    "SourceVersionHash": "iQ/+oerXTV9RInXtlauTg30TuvQ=",
    "VersionHash": "G/UvrA84lSiYex1/Vx7yOo42M1M="
  },
  "19,64": {
    "SourceVersionHash": "iQ/+oerXTV9RInXtlauTg30TuvQ=",
    "VersionHash": "G/UvrA84lSiYex1/Vx7yOo42M1M="
  },
  "18,64": {
    "SourceVersionHash": "iQ/+oerXTV9RInXtlauTg30TuvQ=",
    "VersionHash": "G/UvrA84lSiYex1/Vx7yOo42M1M="
  },
  "17,64": {
    "SourceVersionHash": "iQ/+oerXTV9RInXtlauTg30TuvQ=",
    "VersionHash": "G/UvrA84lSiYex1/Vx7yOo42M1M="
  },
  "16,64": {
    "SourceVersionHash": "iQ/+oerXTV9RInXtlauTg30TuvQ=",
    "VersionHash": "G/UvrA84lSiYex1/Vx7yOo42M1M="
  },
  "15,64": {
    "SourceVersionHash": "e3exm8NTn7dchXOM1ME3TpXE04U=",
    "VersionHash": "G/UvrA84lSiYex1/Vx7yOo42M1M="
  }
}